{
 "custom_fields": [
  {
   "_assign": null,
   "_comments": null,
   "_liked_by": null,
   "_user_tags": null,
   "allow_in_quick_entry": 0,
   "allow_on_submit": 0,
   "bold": 0,
   "collapsible": 0,
   "collapsible_depends_on": null,
   "columns": 0,
   "creation": "2023-11-03 11:55:40.121171",
   "default": null,
   "depends_on": null,
   "description": null,
   "docstatus": 0,
   "dt": "Colending Partner",
   "fetch_from": null,
   "fetch_if_empty": 0,
   "fieldname": "kinara_details_section",
   "fieldtype": "Section Break",
   "hidden": 0,
   "hide_border": 0,
   "hide_days": 0,
   "hide_seconds": 0,
   "idx": 0,
   "ignore_user_permissions": 0,
   "ignore_xss_filter": 0,
   "in_global_search": 0,
   "in_list_view": 0,
   "in_preview": 0,
   "in_standard_filter": 0,
   "insert_after": "partial_payment_mechanism",
   "is_system_generated": 1,
   "is_virtual": 0,
   "label": "Kinara Details",
   "length": 0,
   "link_filters": null,
   "mandatory_depends_on": null,
   "modified": "2023-11-03 11:55:40.121171",
   "modified_by": "Administrator",
   "module": null,
   "name": "Loan Partner-kinara_details_section",
   "no_copy": 0,
   "non_negative": 0,
   "options": null,
   "owner": "Administrator",
   "permlevel": 0,
   "precision": "",
   "print_hide": 0,
   "print_hide_if_no_value": 0,
   "print_width": null,
   "read_only": 0,
   "read_only_depends_on": null,
   "report_hide": 0,
   "reqd": 0,
   "search_index": 0,
   "sort_options": 0,
   "translatable": 1,
   "unique": 0,
   "width": null
  },
  {
   "_assign": null,
   "_comments": null,
   "_liked_by": null,
   "_user_tags": null,
   "allow_in_quick_entry": 0,
   "allow_on_submit": 0,
   "bold": 0,
   "collapsible": 0,
   "collapsible_depends_on": null,
   "columns": 0,
   "creation": "2023-10-03 01:24:57.073303",
   "default": null,
   "depends_on": null,
   "description": null,
   "docstatus": 0,
   "dt": "Colending Partner",
   "fetch_from": null,
   "fetch_if_empty": 0,
   "fieldname": "processing_fee_billing",
   "fieldtype": "Percent",
   "hidden": 0,
   "hide_border": 0,
   "hide_days": 0,
   "hide_seconds": 0,
   "idx": 0,
   "ignore_user_permissions": 0,
   "ignore_xss_filter": 0,
   "in_global_search": 0,
   "in_list_view": 0,
   "in_preview": 0,
   "in_standard_filter": 0,
   "insert_after": "kinara_details_section",
   "is_system_generated": 1,
   "is_virtual": 0,
   "label": "Processing Fee Billing (against partner share)",
   "length": 0,
   "link_filters": null,
   "mandatory_depends_on": null,
   "modified": "2023-11-03 11:55:40.162080",
   "modified_by": "Administrator",
   "module": null,
   "name": "Loan Partner-processing_fee_billing",
   "no_copy": 0,
   "non_negative": 0,
   "options": null,
   "owner": "Administrator",
   "permlevel": 0,
   "precision": "",
   "print_hide": 0,
   "print_hide_if_no_value": 0,
   "print_width": null,
   "read_only": 0,
   "read_only_depends_on": null,
   "report_hide": 0,
   "reqd": 0,
   "search_index": 0,
   "sort_options": 0,
   "translatable": 1,
   "unique": 0,
   "width": null
  },
  {
   "_assign": null,
   "_comments": null,
   "_liked_by": null,
   "_user_tags": null,
   "allow_in_quick_entry": 0,
   "allow_on_submit": 0,
   "bold": 0,
   "collapsible": 0,
   "collapsible_depends_on": null,
   "columns": 0,
   "creation": "2023-11-03 11:55:40.238839",
   "default": "0",
   "depends_on": null,
   "description": null,
   "docstatus": 0,
   "dt": "Colending Partner",
   "fetch_from": null,
   "fetch_if_empty": 0,
   "fieldname": "kinara_security_emi_shared",
   "fieldtype": "Check",
   "hidden": 0,
   "hide_border": 0,
   "hide_days": 0,
   "hide_seconds": 0,
   "idx": 0,
   "ignore_user_permissions": 0,
   "ignore_xss_filter": 0,
   "in_global_search": 0,
   "in_list_view": 0,
   "in_preview": 0,
   "in_standard_filter": 0,
   "insert_after": "processing_fee_billing",
   "is_system_generated": 1,
   "is_virtual": 0,
   "label": "Security EMI shared",
   "length": 0,
   "link_filters": null,
   "mandatory_depends_on": null,
   "modified": "2023-11-03 11:55:40.238839",
   "modified_by": "Administrator",
   "module": null,
   "name": "Loan Partner-kinara_security_emi_shared",
   "no_copy": 0,
   "non_negative": 0,
   "options": null,
   "owner": "Administrator",
   "permlevel": 0,
   "precision": "",
   "print_hide": 0,
   "print_hide_if_no_value": 0,
   "print_width": null,
   "read_only": 0,
   "read_only_depends_on": null,
   "report_hide": 0,
   "reqd": 0,
   "search_index": 0,
   "sort_options": 0,
   "translatable": 1,
   "unique": 0,
   "width": null
  },
  {
   "_assign": null,
   "_comments": null,
   "_liked_by": null,
   "_user_tags": null,
   "allow_in_quick_entry": 0,
   "allow_on_submit": 0,
   "bold": 0,
   "collapsible": 0,
   "collapsible_depends_on": null,
   "columns": 0,
   "creation": "2023-11-03 11:55:40.247082",
   "default": null,
   "depends_on": "eval:doc.kinara_security_emi_shared;",
   "description": null,
   "docstatus": 0,
   "dt": "Colending Partner",
   "fetch_from": null,
   "fetch_if_empty": 0,
   "fieldname": "kinara_security_emi_partner_ratio",
   "fieldtype": "Percent",
   "hidden": 0,
   "hide_border": 0,
   "hide_days": 0,
   "hide_seconds": 0,
   "idx": 0,
   "ignore_user_permissions": 0,
   "ignore_xss_filter": 0,
   "in_global_search": 0,
   "in_list_view": 0,
   "in_preview": 0,
   "in_standard_filter": 0,
   "insert_after": "kinara_security_emi_shared",
   "is_system_generated": 1,
   "is_virtual": 0,
   "label": "Security EMI Partner Ratio",
   "length": 0,
   "link_filters": null,
   "mandatory_depends_on": null,
   "modified": "2023-11-03 11:55:40.247082",
   "modified_by": "Administrator",
   "module": null,
   "name": "Loan Partner-kinara_security_emi_partner_ratio",
   "no_copy": 0,
   "non_negative": 0,
   "options": null,
   "owner": "Administrator",
   "permlevel": 0,
   "precision": "",
   "print_hide": 0,
   "print_hide_if_no_value": 0,
   "print_width": null,
   "read_only": 0,
   "read_only_depends_on": null,
   "report_hide": 0,
   "reqd": 0,
   "search_index": 0,
   "sort_options": 0,
   "translatable": 1,
   "unique": 0,
   "width": null
  },
  {
   "_assign": null,
   "_comments": null,
   "_liked_by": null,
   "_user_tags": null,
   "allow_in_quick_entry": 0,
   "allow_on_submit": 0,
   "bold": 0,
   "collapsible": 0,
   "collapsible_depends_on": null,
   "columns": 0,
   "creation": "2023-11-03 11:55:40.254834",
   "default": null,
   "depends_on": "eval:doc.kinara_security_emi_shared;",
   "description": null,
   "docstatus": 0,
   "dt": "Colending Partner",
   "fetch_from": null,
   "fetch_if_empty": 0,
   "fieldname": "kinara_security_emi_own_ratio",
   "fieldtype": "Percent",
   "hidden": 0,
   "hide_border": 0,
   "hide_days": 0,
   "hide_seconds": 0,
   "idx": 0,
   "ignore_user_permissions": 0,
   "ignore_xss_filter": 0,
   "in_global_search": 0,
   "in_list_view": 0,
   "in_preview": 0,
   "in_standard_filter": 0,
   "insert_after": "kinara_security_emi_partner_ratio",
   "is_system_generated": 1,
   "is_virtual": 0,
   "label": "Security EMI Own Ratio",
   "length": 0,
   "link_filters": null,
   "mandatory_depends_on": null,
   "modified": "2023-11-03 11:55:40.254834",
   "modified_by": "Administrator",
   "module": null,
   "name": "Loan Partner-kinara_security_emi_own_ratio",
   "no_copy": 0,
   "non_negative": 0,
   "options": null,
   "owner": "Administrator",
   "permlevel": 0,
   "precision": "",
   "print_hide": 0,
   "print_hide_if_no_value": 0,
   "print_width": null,
   "read_only": 0,
   "read_only_depends_on": null,
   "report_hide": 0,
   "reqd": 0,
   "search_index": 0,
   "sort_options": 0,
   "translatable": 1,
   "unique": 0,
   "width": null
  },
  {
   "_assign": null,
   "_comments": null,
   "_liked_by": null,
   "_user_tags": null,
   "allow_in_quick_entry": 0,
   "allow_on_submit": 0,
   "bold": 0,
   "collapsible": 0,
   "collapsible_depends_on": null,
   "columns": 0,
   "creation": "2023-12-08 16:19:43.470362",
   "default": null,
   "depends_on": null,
   "description": null,
   "docstatus": 0,
   "dt": "Colending Partner",
   "fetch_from": null,
   "fetch_if_empty": 0,
   "fieldname": "partner_cin",
   "fieldtype": "Data",
   "hidden": 0,
   "hide_border": 0,
   "hide_days": 0,
   "hide_seconds": 0,
   "idx": 4,
   "ignore_user_permissions": 0,
   "ignore_xss_filter": 0,
   "in_global_search": 0,
   "in_list_view": 0,
   "in_preview": 0,
   "in_standard_filter": 0,
   "insert_after": "partner_name",
   "is_system_generated": 0,
   "is_virtual": 0,
   "label": "Partner CIN",
   "length": 0,
   "link_filters": null,
   "mandatory_depends_on": null,
   "modified": "2023-12-01 16:30:12.674556",
   "modified_by": "Administrator",
   "module": null,
   "name": "Loan Partner-custom_partner_cin",
   "no_copy": 0,
   "non_negative": 0,
   "options": null,
   "owner": null,
   "permlevel": 0,
   "precision": "",
   "print_hide": 0,
   "print_hide_if_no_value": 0,
   "print_width": null,
   "read_only": 0,
   "read_only_depends_on": null,
   "report_hide": 0,
   "reqd": 0,
   "search_index": 0,
   "sort_options": 0,
   "translatable": 1,
   "unique": 0,
   "width": null
  },
  {
   "_assign": null,
   "_comments": null,
   "_liked_by": null,
   "_user_tags": null,
   "allow_in_quick_entry": 0,
   "allow_on_submit": 0,
   "bold": 0,
   "collapsible": 0,
   "collapsible_depends_on": null,
   "columns": 0,
   "creation": "2023-12-08 16:19:44.373575",
   "default": null,
   "depends_on": null,
   "description": null,
   "docstatus": 0,
   "dt": "Colending Partner",
   "fetch_from": null,
   "fetch_if_empty": 0,
   "fieldname": "partner_rbi",
   "fieldtype": "Data",
   "hidden": 0,
   "hide_border": 0,
   "hide_days": 0,
   "hide_seconds": 0,
   "idx": 5,
   "ignore_user_permissions": 0,
   "ignore_xss_filter": 0,
   "in_global_search": 0,
   "in_list_view": 0,
   "in_preview": 0,
   "in_standard_filter": 0,
   "insert_after": "partner_cin",
   "is_system_generated": 0,
   "is_virtual": 0,
   "label": "Partner RBI",
   "length": 0,
   "link_filters": null,
   "mandatory_depends_on": null,
   "modified": "2023-12-01 16:30:51.576872",
   "modified_by": "Administrator",
   "module": null,
   "name": "Loan Partner-custom_partner_rbi",
   "no_copy": 0,
   "non_negative": 0,
   "options": null,
   "owner": null,
   "permlevel": 0,
   "precision": "",
   "print_hide": 0,
   "print_hide_if_no_value": 0,
   "print_width": null,
   "read_only": 0,
   "read_only_depends_on": null,
   "report_hide": 0,
   "reqd": 0,
   "search_index": 0,
   "sort_options": 0,
   "translatable": 1,
   "unique": 0,
   "width": null
  },
  {
   "_assign": null,
   "_comments": null,
   "_liked_by": null,
   "_user_tags": null,
   "allow_in_quick_entry": 0,
   "allow_on_submit": 0,
   "bold": 0,
   "collapsible": 0,
   "collapsible_depends_on": null,
   "columns": 0,
   "creation": "2023-12-08 16:19:47.122338",
   "default": null,
   "depends_on": null,
   "description": null,
   "docstatus": 0,
   "dt": "Colending Partner",
   "fetch_from": null,
   "fetch_if_empty": 0,
   "fieldname": "partner_full_name",
   "fieldtype": "Data",
   "hidden": 0,
   "hide_border": 0,
   "hide_days": 0,
   "hide_seconds": 0,
   "idx": 6,
   "ignore_user_permissions": 0,
   "ignore_xss_filter": 0,
   "in_global_search": 0,
   "in_list_view": 0,
   "in_preview": 0,
   "in_standard_filter": 0,
   "insert_after": "partner_rbi",
   "is_system_generated": 0,
   "is_virtual": 0,
   "label": "Partner Full Name",
   "length": 0,
   "link_filters": null,
   "mandatory_depends_on": null,
   "modified": "2023-12-01 16:30:51.614887",
   "modified_by": "Administrator",
   "module": null,
   "name": "Loan Partner-custom_partner_full_name",
   "no_copy": 0,
   "non_negative": 0,
   "options": null,
   "owner": null,
   "permlevel": 0,
   "precision": "",
   "print_hide": 0,
   "print_hide_if_no_value": 0,
   "print_width": null,
   "read_only": 0,
   "read_only_depends_on": null,
   "report_hide": 0,
   "reqd": 0,
   "search_index": 0,
   "sort_options": 0,
   "translatable": 1,
   "unique": 0,
   "width": null
  },
  {
   "_assign": null,
   "_comments": null,
   "_liked_by": null,
   "_user_tags": null,
   "allow_in_quick_entry": 0,
   "allow_on_submit": 0,
   "bold": 0,
   "collapsible": 0,
   "collapsible_depends_on": null,
   "columns": 0,
   "creation": "2023-12-08 16:20:16.959874",
   "default": null,
   "depends_on": null,
   "description": null,
   "docstatus": 0,
   "dt": "Colending Partner",
   "fetch_from": null,
   "fetch_if_empty": 0,
   "fieldname": "ifsc_code_collections",
   "fieldtype": "Link",
   "hidden": 0,
   "hide_border": 0,
   "hide_days": 0,
   "hide_seconds": 0,
   "idx": 26,
   "ignore_user_permissions": 0,
   "ignore_xss_filter": 0,
   "in_global_search": 0,
   "in_list_view": 0,
   "in_preview": 0,
   "in_standard_filter": 0,
   "insert_after": "custom_column_break_xt3gw",
   "is_system_generated": 0,
   "is_virtual": 0,
   "label": "IFSC Code (Collections)",
   "length": 0,
   "link_filters": null,
   "mandatory_depends_on": null,
   "modified": "2023-12-01 16:31:59.482606",
   "modified_by": "Administrator",
   "module": null,
   "name": "Loan Partner-custom_ifsc_code_collections",
   "no_copy": 0,
   "non_negative": 0,
   "options": "IFSC Code",
   "owner": null,
   "permlevel": 0,
   "precision": "",
   "print_hide": 0,
   "print_hide_if_no_value": 0,
   "print_width": null,
   "read_only": 0,
   "read_only_depends_on": null,
   "report_hide": 0,
   "reqd": 0,
   "search_index": 0,
   "sort_options": 0,
   "translatable": 0,
   "unique": 0,
   "width": null
  },
  {
   "_assign": null,
   "_comments": null,
   "_liked_by": null,
   "_user_tags": null,
   "allow_in_quick_entry": 0,
   "allow_on_submit": 0,
   "bold": 0,
   "collapsible": 0,
   "collapsible_depends_on": null,
   "columns": 0,
   "creation": "2023-12-08 16:20:17.363383",
   "default": null,
   "depends_on": null,
   "description": null,
   "docstatus": 0,
   "dt": "Colending Partner",
   "fetch_from": null,
   "fetch_if_empty": 0,
   "fieldname": "escrow_applicable_flag_collections",
   "fieldtype": "Check",
   "hidden": 0,
   "hide_border": 0,
   "hide_days": 0,
   "hide_seconds": 0,
   "idx": 27,
   "ignore_user_permissions": 0,
   "ignore_xss_filter": 0,
   "in_global_search": 0,
   "in_list_view": 0,
   "in_preview": 0,
   "in_standard_filter": 0,
   "insert_after": "ifsc_code_collections",
   "is_system_generated": 0,
   "is_virtual": 0,
   "label": "ESCROW Applicable Flag (Collections)",
   "length": 0,
   "link_filters": null,
   "mandatory_depends_on": null,
   "modified": "2023-12-01 16:31:59.520852",
   "modified_by": "Administrator",
   "module": null,
   "name": "Loan Partner-custom_escrow_applicable_flag_collections",
   "no_copy": 0,
   "non_negative": 0,
   "options": null,
   "owner": null,
   "permlevel": 0,
   "precision": "",
   "print_hide": 0,
   "print_hide_if_no_value": 0,
   "print_width": null,
   "read_only": 0,
   "read_only_depends_on": null,
   "report_hide": 0,
   "reqd": 0,
   "search_index": 0,
   "sort_options": 0,
   "translatable": 0,
   "unique": 0,
   "width": null
  },
  {
   "_assign": null,
   "_comments": null,
   "_liked_by": null,
   "_user_tags": null,
   "allow_in_quick_entry": 0,
   "allow_on_submit": 0,
   "bold": 0,
   "collapsible": 0,
   "collapsible_depends_on": null,
   "columns": 0,
   "creation": "2023-12-08 16:20:02.631422",
   "default": null,
   "depends_on": "escrow_applicable_flag_disbursement",
   "description": null,
   "docstatus": 0,
   "dt": "Colending Partner",
   "fetch_from": null,
   "fetch_if_empty": 0,
   "fieldname": "bank_name_disbursement",
   "fieldtype": "Link",
   "hidden": 0,
   "hide_border": 0,
   "hide_days": 0,
   "hide_seconds": 0,
   "idx": 18,
   "ignore_user_permissions": 0,
   "ignore_xss_filter": 0,
   "in_global_search": 0,
   "in_list_view": 0,
   "in_preview": 0,
   "in_standard_filter": 0,
   "insert_after": "escrow_applicable_flag_disbursement",
   "is_system_generated": 0,
   "is_virtual": 0,
   "label": "Bank Name (Disbursement)",
   "length": 0,
   "link_filters": null,
   "mandatory_depends_on": null,
   "modified": "2023-12-01 16:32:24.878626",
   "modified_by": "Administrator",
   "module": null,
   "name": "Loan Partner-custom_bank_name_disbursement",
   "no_copy": 0,
   "non_negative": 0,
   "options": "Bank",
   "owner": null,
   "permlevel": 0,
   "precision": "",
   "print_hide": 0,
   "print_hide_if_no_value": 0,
   "print_width": null,
   "read_only": 0,
   "read_only_depends_on": null,
   "report_hide": 0,
   "reqd": 0,
   "search_index": 0,
   "sort_options": 0,
   "translatable": 0,
   "unique": 0,
   "width": null
  },
  {
   "_assign": null,
   "_comments": null,
   "_liked_by": null,
   "_user_tags": null,
   "allow_in_quick_entry": 0,
   "allow_on_submit": 0,
   "bold": 0,
   "collapsible": 0,
   "collapsible_depends_on": null,
   "columns": 0,
   "creation": "2023-12-08 16:20:11.493061",
   "default": null,
   "depends_on": "escrow_applicable_flag_disbursement",
   "description": null,
   "docstatus": 0,
   "dt": "Colending Partner",
   "fetch_from": null,
   "fetch_if_empty": 0,
   "fieldname": "ifsc_code_disbursement",
   "fieldtype": "Link",
   "hidden": 0,
   "hide_border": 0,
   "hide_days": 0,
   "hide_seconds": 0,
   "idx": 18,
   "ignore_user_permissions": 0,
   "ignore_xss_filter": 0,
   "in_global_search": 0,
   "in_list_view": 0,
   "in_preview": 0,
   "in_standard_filter": 0,
   "insert_after": "bank_name_disbursement",
   "is_system_generated": 0,
   "is_virtual": 0,
   "label": "IFSC Code (Disbursement)",
   "length": 0,
   "link_filters": null,
   "mandatory_depends_on": null,
   "modified": "2023-12-01 16:32:47.296139",
   "modified_by": "Administrator",
   "module": null,
   "name": "Loan Partner-custom_ifsc_code_disbursement",
   "no_copy": 0,
   "non_negative": 0,
   "options": "IFSC Code",
   "owner": null,
   "permlevel": 0,
   "precision": "",
   "print_hide": 0,
   "print_hide_if_no_value": 0,
   "print_width": null,
   "read_only": 0,
   "read_only_depends_on": null,
   "report_hide": 0,
   "reqd": 0,
   "search_index": 0,
   "sort_options": 0,
   "translatable": 0,
   "unique": 0,
   "width": null
  },
  {
   "_assign": null,
   "_comments": null,
   "_liked_by": null,
   "_user_tags": null,
   "allow_in_quick_entry": 0,
   "allow_on_submit": 0,
   "bold": 0,
   "collapsible": 0,
   "collapsible_depends_on": null,
   "columns": 0,
   "creation": "2023-12-08 16:20:12.661714",
   "default": null,
   "depends_on": null,
   "description": null,
   "docstatus": 0,
   "dt": "Colending Partner",
   "fetch_from": null,
   "fetch_if_empty": 0,
   "fieldname": "escrow_applicable_flag_disbursement",
   "fieldtype": "Check",
   "hidden": 0,
   "hide_border": 0,
   "hide_days": 0,
   "hide_seconds": 0,
   "idx": 17,
   "ignore_user_permissions": 0,
   "ignore_xss_filter": 0,
   "in_global_search": 0,
   "in_list_view": 0,
   "in_preview": 0,
   "in_standard_filter": 0,
   "insert_after": "custom_disbursement_details",
   "is_system_generated": 0,
   "is_virtual": 0,
   "label": "ESCROW Applicable Flag (Disbursement)",
   "length": 0,
   "link_filters": null,
   "mandatory_depends_on": null,
   "modified": "2023-12-01 16:33:51.396456",
   "modified_by": "Administrator",
   "module": null,
   "name": "Loan Partner-custom_escrow_applicable_flag_disbursement",
   "no_copy": 0,
   "non_negative": 0,
   "options": null,
   "owner": null,
   "permlevel": 0,
   "precision": "",
   "print_hide": 0,
   "print_hide_if_no_value": 0,
   "print_width": null,
   "read_only": 0,
   "read_only_depends_on": null,
   "report_hide": 0,
   "reqd": 0,
   "search_index": 0,
   "sort_options": 0,
   "translatable": 0,
   "unique": 0,
   "width": null
  },
  {
   "_assign": null,
   "_comments": null,
   "_liked_by": null,
   "_user_tags": null,
   "allow_in_quick_entry": 0,
   "allow_on_submit": 0,
   "bold": 0,
   "collapsible": 0,
   "collapsible_depends_on": null,
   "columns": 0,
   "creation": "2023-12-08 16:20:13.743924",
   "default": null,
   "depends_on": null,
   "description": null,
   "docstatus": 0,
   "dt": "Colending Partner",
   "fetch_from": null,
   "fetch_if_empty": 0,
   "fieldname": "custom_collections_details",
   "fieldtype": "Section Break",
   "hidden": 0,
   "hide_border": 0,
   "hide_days": 0,
   "hide_seconds": 0,
   "idx": 22,
   "ignore_user_permissions": 0,
   "ignore_xss_filter": 0,
   "in_global_search": 0,
   "in_list_view": 0,
   "in_preview": 0,
   "in_standard_filter": 0,
   "insert_after": "custom_column_break_xsx3x",
   "is_system_generated": 0,
   "is_virtual": 0,
   "label": "Collections Details",
   "length": 0,
   "link_filters": null,
   "mandatory_depends_on": null,
   "modified": "2023-12-01 16:33:51.419091",
   "modified_by": "Administrator",
   "module": null,
   "name": "Loan Partner-custom_collections_details",
   "no_copy": 0,
   "non_negative": 0,
   "options": null,
   "owner": null,
   "permlevel": 0,
   "precision": "",
   "print_hide": 0,
   "print_hide_if_no_value": 0,
   "print_width": null,
   "read_only": 0,
   "read_only_depends_on": null,
   "report_hide": 0,
   "reqd": 0,
   "search_index": 0,
   "sort_options": 0,
   "translatable": 0,
   "unique": 0,
   "width": null
  },
  {
   "_assign": null,
   "_comments": null,
   "_liked_by": null,
   "_user_tags": null,
   "allow_in_quick_entry": 0,
   "allow_on_submit": 0,
   "bold": 0,
   "collapsible": 0,
   "collapsible_depends_on": null,
   "columns": 0,
   "creation": "2023-12-08 16:20:06.288844",
   "default": null,
   "depends_on": "escrow_applicable_flag_disbursement",
   "description": null,
   "docstatus": 0,
   "dt": "Colending Partner",
   "fetch_from": null,
   "fetch_if_empty": 0,
   "fieldname": "bank_account_number_disbursement",
   "fieldtype": "Link",
   "hidden": 0,
   "hide_border": 0,
   "hide_days": 0,
   "hide_seconds": 0,
   "idx": 19,
   "ignore_user_permissions": 0,
   "ignore_xss_filter": 0,
   "in_global_search": 0,
   "in_list_view": 0,
   "in_preview": 0,
   "in_standard_filter": 0,
   "insert_after": "ifsc_code_disbursement",
   "is_system_generated": 0,
   "is_virtual": 0,
   "label": "Bank Account Number (Disbursement)",
   "length": 0,
   "link_filters": null,
   "mandatory_depends_on": null,
   "modified": "2023-12-01 16:34:11.196237",
   "modified_by": "Administrator",
   "module": null,
   "name": "Loan Partner-custom_bank_account_number_disbursement",
   "no_copy": 0,
   "non_negative": 0,
   "options": "Bank Account",
   "owner": null,
   "permlevel": 0,
   "precision": "",
   "print_hide": 0,
   "print_hide_if_no_value": 0,
   "print_width": null,
   "read_only": 0,
   "read_only_depends_on": null,
   "report_hide": 0,
   "reqd": 0,
   "search_index": 0,
   "sort_options": 0,
   "translatable": 0,
   "unique": 0,
   "width": null
  },
  {
   "_assign": null,
   "_comments": null,
   "_liked_by": null,
   "_user_tags": null,
   "allow_in_quick_entry": 0,
   "allow_on_submit": 0,
   "bold": 0,
   "collapsible": 0,
   "collapsible_depends_on": null,
   "columns": 0,
   "creation": "2023-12-08 16:20:09.513822",
   "default": null,
   "depends_on": null,
   "description": null,
   "docstatus": 0,
   "dt": "Colending Partner",
   "fetch_from": null,
   "fetch_if_empty": 0,
   "fieldname": "custom_column_break_xsx3x",
   "fieldtype": "Column Break",
   "hidden": 0,
   "hide_border": 0,
   "hide_days": 0,
   "hide_seconds": 0,
   "idx": 20,
   "ignore_user_permissions": 0,
   "ignore_xss_filter": 0,
   "in_global_search": 0,
   "in_list_view": 0,
   "in_preview": 0,
   "in_standard_filter": 0,
   "insert_after": "bank_account_number_disbursement",
   "is_system_generated": 0,
   "is_virtual": 0,
   "label": null,
   "length": 0,
   "link_filters": null,
   "mandatory_depends_on": null,
   "modified": "2023-12-01 16:34:11.233742",
   "modified_by": "Administrator",
   "module": null,
   "name": "Loan Partner-custom_column_break_xsx3x",
   "no_copy": 0,
   "non_negative": 0,
   "options": null,
   "owner": null,
   "permlevel": 0,
   "precision": "",
   "print_hide": 0,
   "print_hide_if_no_value": 0,
   "print_width": null,
   "read_only": 0,
   "read_only_depends_on": null,
   "report_hide": 0,
   "reqd": 0,
   "search_index": 0,
   "sort_options": 0,
   "translatable": 0,
   "unique": 0,
   "width": null
  },
  {
   "_assign": null,
   "_comments": null,
   "_liked_by": null,
   "_user_tags": null,
   "allow_in_quick_entry": 0,
   "allow_on_submit": 0,
   "bold": 0,
   "collapsible": 0,
   "collapsible_depends_on": null,
   "columns": 0,
   "creation": "2023-12-08 16:20:15.936014",
   "default": null,
   "depends_on": null,
   "description": null,
   "docstatus": 0,
   "dt": "Colending Partner",
   "fetch_from": null,
   "fetch_if_empty": 0,
   "fieldname": "custom_column_break_xt3gw",
   "fieldtype": "Column Break",
   "hidden": 0,
   "hide_border": 0,
   "hide_days": 0,
   "hide_seconds": 0,
   "idx": 25,
   "ignore_user_permissions": 0,
   "ignore_xss_filter": 0,
   "in_global_search": 0,
   "in_list_view": 0,
   "in_preview": 0,
   "in_standard_filter": 0,
   "insert_after": "bank_account_number_collections",
   "is_system_generated": 0,
   "is_virtual": 0,
   "label": null,
   "length": 0,
   "link_filters": null,
   "mandatory_depends_on": null,
   "modified": "2023-12-01 16:35:00.397785",
   "modified_by": "Administrator",
   "module": null,
   "name": "Loan Partner-custom_column_break_xt3gw",
   "no_copy": 0,
   "non_negative": 0,
   "options": null,
   "owner": null,
   "permlevel": 0,
   "precision": "",
   "print_hide": 0,
   "print_hide_if_no_value": 0,
   "print_width": null,
   "read_only": 0,
   "read_only_depends_on": null,
   "report_hide": 0,
   "reqd": 0,
   "search_index": 0,
   "sort_options": 0,
   "translatable": 0,
   "unique": 0,
   "width": null
  },
  {
   "_assign": null,
   "_comments": null,
   "_liked_by": null,
   "_user_tags": null,
   "allow_in_quick_entry": 0,
   "allow_on_submit": 0,
   "bold": 0,
   "collapsible": 0,
   "collapsible_depends_on": null,
   "columns": 0,
   "creation": "2023-12-08 16:20:14.195170",
   "default": null,
   "depends_on": null,
   "description": null,
   "docstatus": 0,
   "dt": "Colending Partner",
   "fetch_from": null,
   "fetch_if_empty": 0,
   "fieldname": "bank_name_collections",
   "fieldtype": "Link",
   "hidden": 0,
   "hide_border": 0,
   "hide_days": 0,
   "hide_seconds": 0,
   "idx": 23,
   "ignore_user_permissions": 0,
   "ignore_xss_filter": 0,
   "in_global_search": 0,
   "in_list_view": 0,
   "in_preview": 0,
   "in_standard_filter": 0,
   "insert_after": "custom_collections_details",
   "is_system_generated": 0,
   "is_virtual": 0,
   "label": "Bank Name (Collections)",
   "length": 0,
   "link_filters": null,
   "mandatory_depends_on": null,
   "modified": "2023-12-01 16:35:20.050374",
   "modified_by": "Administrator",
   "module": null,
   "name": "Loan Partner-custom_bank_name_collections",
   "no_copy": 0,
   "non_negative": 0,
   "options": "Bank",
   "owner": null,
   "permlevel": 0,
   "precision": "",
   "print_hide": 0,
   "print_hide_if_no_value": 0,
   "print_width": null,
   "read_only": 0,
   "read_only_depends_on": null,
   "report_hide": 0,
   "reqd": 0,
   "search_index": 0,
   "sort_options": 0,
   "translatable": 0,
   "unique": 0,
   "width": null
  },
  {
   "_assign": null,
   "_comments": null,
   "_liked_by": null,
   "_user_tags": null,
   "allow_in_quick_entry": 0,
   "allow_on_submit": 0,
   "bold": 0,
   "collapsible": 0,
   "collapsible_depends_on": null,
   "columns": 0,
   "creation": "2023-12-08 16:20:15.449574",
   "default": null,
   "depends_on": null,
   "description": null,
   "docstatus": 0,
   "dt": "Colending Partner",
   "fetch_from": null,
   "fetch_if_empty": 0,
   "fieldname": "bank_account_number_collections",
   "fieldtype": "Data",
   "hidden": 0,
   "hide_border": 0,
   "hide_days": 0,
   "hide_seconds": 0,
   "idx": 24,
   "ignore_user_permissions": 0,
   "ignore_xss_filter": 0,
   "in_global_search": 0,
   "in_list_view": 0,
   "in_preview": 0,
   "in_standard_filter": 0,
   "insert_after": "bank_name_collections",
   "is_system_generated": 0,
   "is_virtual": 0,
   "label": "Bank Account Number (Collections)",
   "length": 0,
   "link_filters": null,
   "mandatory_depends_on": null,
   "modified": "2023-12-01 16:35:20.086517",
   "modified_by": "Administrator",
   "module": null,
   "name": "Loan Partner-custom_bank_account_number_collections",
   "no_copy": 0,
   "non_negative": 0,
   "options": null,
   "owner": null,
   "permlevel": 0,
   "precision": "",
   "print_hide": 0,
   "print_hide_if_no_value": 0,
   "print_width": null,
   "read_only": 0,
   "read_only_depends_on": null,
   "report_hide": 0,
   "reqd": 0,
   "search_index": 0,
   "sort_options": 0,
   "translatable": 1,
   "unique": 0,
   "width": null
  },
  {
   "_assign": null,
   "_comments": null,
   "_liked_by": null,
   "_user_tags": null,
   "allow_in_quick_entry": 0,
   "allow_on_submit": 0,
   "bold": 0,
   "collapsible": 0,
   "collapsible_depends_on": null,
   "columns": 0,
   "creation": "2023-12-08 16:19:58.596819",
   "default": null,
   "depends_on": null,
   "description": null,
   "docstatus": 0,
   "dt": "Colending Partner",
   "fetch_from": null,
   "fetch_if_empty": 0,
   "fieldname": "custom_disbursement_details",
   "fieldtype": "Section Break",
   "hidden": 0,
   "hide_border": 0,
   "hide_days": 0,
   "hide_seconds": 0,
   "idx": 16,
   "ignore_user_permissions": 0,
   "ignore_xss_filter": 0,
   "in_global_search": 0,
   "in_list_view": 0,
   "in_preview": 0,
   "in_standard_filter": 0,
   "insert_after": "incremental_interest_applicable",
   "is_system_generated": 0,
   "is_virtual": 0,
   "label": "Disbursement Details",
   "length": 0,
   "link_filters": null,
   "mandatory_depends_on": null,
   "modified": "2023-12-06 17:20:02.080400",
   "modified_by": "Administrator",
   "module": null,
   "name": "Loan Partner-custom_disbursement_details",
   "no_copy": 0,
   "non_negative": 0,
   "options": null,
   "owner": null,
   "permlevel": 0,
   "precision": "",
   "print_hide": 0,
   "print_hide_if_no_value": 0,
   "print_width": null,
   "read_only": 0,
   "read_only_depends_on": null,
   "report_hide": 0,
   "reqd": 0,
   "search_index": 0,
   "sort_options": 0,
   "translatable": 0,
   "unique": 0,
   "width": null
  }
 ],
 "custom_perms": [],
 "doctype": "Colending Partner",
 "links": [],
 "property_setters": [
  {
   "_assign": null,
   "_comments": null,
   "_liked_by": null,
   "_user_tags": null,
   "creation": "2023-12-08 18:20:11.203445",
   "default_value": null,
   "doc_type": "Colending Partner",
   "docstatus": 0,
   "doctype_or_field": "DocType",
   "field_name": null,
   "idx": 0,
   "is_system_generated": 0,
   "modified": "2023-12-08 18:20:11.203445",
   "modified_by": "Administrator",
   "module": null,
   "name": "Loan Partner-main-field_order",
   "owner": "Administrator",
   "property": "field_order",
   "property_type": "Data",
   "row_name": null,
   "value": "[\"details_section\", \"partner_code\", \"partner_name\", \"partner_cin\", \"partner_rbi\", \"partner_full_name\", \"partner_base_interest_rate\", \"column_break_yfag\", \"repayment_schedule_type\", \"partner_loan_share_percentage\", \"effective_date\", \"company_loan_share_percentage\", \"company_base_interest_rate\", \"interest_increment_percentage\", \"incremental_interest_applicable\", \"custom_disbursement_details\", \"escrow_applicable_flag_disbursement\", \"bank_name_disbursement\", \"ifsc_code_disbursement\", \"bank_account_number_disbursement\", \"custom_column_break_xsx3x\", \"custom_collections_details\", \"bank_name_collections\", \"bank_account_number_collections\", \"custom_column_break_xt3gw\", \"ifsc_code_collections\", \"escrow_applicable_flag_collections\", \"section_break_mpap\", \"column_break_gpwj\", \"organization_type\", \"primary_address\", \"column_break_iwpj\", \"address_html\", \"section_break_lpnj\", \"shareables\", \"fldg_section\", \"fldg_trigger_dpd\", \"type_of_fldg_applicable\", \"column_break_szii\", \"fldg_limit_calculation_component\", \"fldg_fixed_deposit_percentage\", \"fldg_corporate_guarantee_percentage\", \"misc_section\", \"servicer_fee\", \"processing_fee_billing\", \"kinara_security_emi_shared\", \"kinara_security_emi_partner_ratio\", \"kinara_security_emi_own_ratio\", \"column_break_wujj\", \"restructure_of_loans_applicable\", \"column_break_xyxj\", \"waiving_of_charges_applicable\", \"section_break_scge\", \"partial_payment_mechanism\"]"
  },
  {
   "_assign": null,
   "_comments": null,
   "_liked_by": null,
   "_user_tags": null,
   "creation": "2023-12-07 16:55:54.720002",
   "default_value": null,
   "doc_type": "Colending Partner",
   "docstatus": 0,
   "doctype_or_field": "DocField",
   "field_name": "partner_name",
   "idx": 0,
   "is_system_generated": 1,
   "modified": "2023-12-07 16:55:54.720002",
   "modified_by": "darshan.s@kinaracapital.com",
   "module": null,
   "name": "Loan Partner-partner_name-in_list_view",
   "owner": "darshan.s@kinaracapital.com",
   "property": "in_list_view",
   "property_type": "Check",
   "row_name": null,
   "value": "1"
  },
  {
   "_assign": null,
   "_comments": null,
   "_liked_by": null,
   "_user_tags": null,
   "creation": "2023-11-02 16:28:23.252301",
   "default_value": null,
   "doc_type": "Colending Partner",
   "docstatus": 0,
   "doctype_or_field": "DocField",
   "field_name": "company_base_interest_rate",
   "idx": 0,
   "is_system_generated": 0,
   "modified": "2023-11-02 16:28:23.252301",
   "modified_by": "darshan.s@kinaracapital.com",
   "module": null,
   "name": "Loan Partner-company_base_interest_rate-label",
   "owner": "darshan.s@kinaracapital.com",
   "property": "label",
   "property_type": "Data",
   "row_name": null,
   "value": "Kinara's base interest rate"
  },
  {
   "_assign": null,
   "_comments": null,
   "_liked_by": null,
   "_user_tags": null,
   "creation": "2023-11-02 16:28:23.187843",
   "default_value": null,
   "doc_type": "Colending Partner",
   "docstatus": 0,
   "doctype_or_field": "DocField",
   "field_name": "company_loan_share_percentage",
   "idx": 0,
   "is_system_generated": 0,
   "modified": "2023-11-02 16:28:23.187843",
   "modified_by": "darshan.s@kinaracapital.com",
   "module": null,
   "name": "Loan Partner-company_loan_share_percentage-label",
   "owner": "darshan.s@kinaracapital.com",
   "property": "label",
   "property_type": "Data",
   "row_name": null,
   "value": "Kinara's Loan Share Percentage"
  },
  {
   "_assign": null,
   "_comments": null,
   "_liked_by": null,
   "_user_tags": null,
   "creation": "2023-10-26 15:41:09.947595",
   "default_value": null,
   "doc_type": "Colending Partner",
   "docstatus": 0,
   "doctype_or_field": "DocField",
   "field_name": "organization_type",
   "idx": 0,
   "is_system_generated": 0,
   "modified": "2023-10-26 15:41:09.947595",
   "modified_by": "darshan.s@kinaracapital.com",
   "module": null,
   "name": "Loan Partner-organization_type-label",
   "owner": "darshan.s@kinaracapital.com",
   "property": "label",
   "property_type": "Data",
   "row_name": null,
   "value": "Partner GST Regime"
  }
 ],
 "sync_on_migrate": 1
}